{
  "circuit_key": 144,
  "name": "Baku",
  "short_name": "Baku",
  "location": "Baku",
  "country": "Azerbaijan",
  "source": "multiviewer",
  "source_url": "https://api.multiviewer.app/api/v1/circuits/144/2026",
  "bounds": {
    "min_x": -16908,
    "max_x": 3724,
    "min_y": -11139,
    "max_y": 3689
  },
  "points": [
    {
      "x": 0.86943,
      "y": 0.71028
    },
    {
      "x": 0.87456,
      "y": 0.71331
    },
    {
      "x": 0.87466,
      "y": 0.71338
    },
    {
      "x": 0.88329,
      "y": 0.71837
    },
    {
      "x": 0.88765,
      "y": 0.72087
    },
    {
      "x": 0.89211,
      "y": 0.7235
    },
    {
      "x": 0.90898,
      "y": 0.73334
    },
    {
      "x": 0.90956,
      "y": 0.73375
    },
    {
      "x": 0.91324,
      "y": 0.73591
    },
    {
      "x": 0.91474,
      "y": 0.73671
    },
    {
      "x": 0.92347,
      "y": 0.74184
    },
    {
      "x": 0.9287,
      "y": 0.74481
    },
    {
      "x": 0.93045,
      "y": 0.74589
    },
    {
      "x": 0.93607,
      "y": 0.74906
    },
    {
      "x": 0.9416,
      "y": 0.75223
    },
    {
      "x": 0.94383,
      "y": 0.75351
    },
    {
      "x": 0.95027,
      "y": 0.75742
    },
    {
      "x": 0.95158,
      "y": 0.75823
    },
    {
      "x": 0.95861,
      "y": 0.76254
    },
    {
      "x": 0.95924,
      "y": 0.76288
    },
    {
      "x": 0.96481,
      "y": 0.76612
    },
    {
      "x": 0.96486,
      "y": 0.76612
    },
    {
      "x": 0.97,
      "y": 0.76888
    },
    {
      "x": 0.97145,
      "y": 0.76956
    },
    {
      "x": 0.97194,
      "y": 0.76976
    },
    {
      "x": 0.97577,
      "y": 0.77158
    },
    {
      "x": 0.97664,
      "y": 0.77205
    },
    {
      "x": 0.98158,
      "y": 0.77455
    },
    {
      "x": 0.98231,
      "y": 0.77495
    },
    {
      "x": 0.98614,
      "y": 0.77738
    },
    {
      "x": 0.98648,
      "y": 0.77758
    },
    {
      "x": 0.98895,
      "y": 0.77947
    },
    {
      "x": 0.99035,
      "y": 0.78082
    },
    {
      "x": 0.99166,
      "y": 0.78224
    },
    {
      "x": 0.99317,
      "y": 0.78399
    },
    {
      "x": 0.99365,
      "y": 0.7846
    },
    {
      "x": 0.99491,
      "y": 0.78615
    },
    {
      "x": 0.99704,
      "y": 0.79026
    },
    {
      "x": 0.99826,
      "y": 0.79363
    },
    {
      "x": 0.99908,
      "y": 0.7962
    },
    {
      "x": 0.99961,
      "y": 0.79808
    },
    {
      "x": 0.9999,
      "y": 0.79997
    },
    {
      "x": 0.99995,
      "y": 0.80159
    },
    {
      "x": 1.0,
      "y": 0.80503
    },
    {
      "x": 1.0,
      "y": 0.80544
    },
    {
      "x": 0.99971,
      "y": 0.80901
    },
    {
      "x": 0.99903,
      "y": 0.81312
    },
    {
      "x": 0.99889,
      "y": 0.81393
    },
    {
      "x": 0.99772,
      "y": 0.81886
    },
    {
      "x": 0.99743,
      "y": 0.81973
    },
    {
      "x": 0.99724,
      "y": 0.82054
    },
    {
      "x": 0.99549,
      "y": 0.82621
    },
    {
      "x": 0.99472,
      "y": 0.8285
    },
    {
      "x": 0.99317,
      "y": 0.83336
    },
    {
      "x": 0.99181,
      "y": 0.83747
    },
    {
      "x": 0.99118,
      "y": 0.83956
    },
    {
      "x": 0.98623,
      "y": 0.85581
    },
    {
      "x": 0.9858,
      "y": 0.85709
    },
    {
      "x": 0.98396,
      "y": 0.8635
    },
    {
      "x": 0.98352,
      "y": 0.86485
    },
    {
      "x": 0.98182,
      "y": 0.87025
    },
    {
      "x": 0.98105,
      "y": 0.87281
    },
    {
      "x": 0.9794,
      "y": 0.87787
    },
    {
      "x": 0.97843,
      "y": 0.88097
    },
    {
      "x": 0.97707,
      "y": 0.88501
    },
    {
      "x": 0.97475,
      "y": 0.89223
    },
    {
      "x": 0.97349,
      "y": 0.89601
    },
    {
      "x": 0.97097,
      "y": 0.90397
    },
    {
      "x": 0.97092,
      "y": 0.90397
    },
    {
      "x": 0.9683,
      "y": 0.91233
    },
    {
      "x": 0.96651,
      "y": 0.91772
    },
    {
      "x": 0.96583,
      "y": 0.92002
    },
    {
      "x": 0.9636,
      "y": 0.92716
    },
    {
      "x": 0.96355,
      "y": 0.92723
    },
    {
      "x": 0.96103,
      "y": 0.93512
    },
    {
      "x": 0.95904,
      "y": 0.94146
    },
    {
      "x": 0.95851,
      "y": 0.94301
    },
    {
      "x": 0.95662,
      "y": 0.94881
    },
    {
      "x": 0.95623,
      "y": 0.95016
    },
    {
      "x": 0.95454,
      "y": 0.95556
    },
    {
      "x": 0.954,
      "y": 0.95711
    },
    {
      "x": 0.95124,
      "y": 0.96588
    },
    {
      "x": 0.95013,
      "y": 0.96925
    },
    {
      "x": 0.94751,
      "y": 0.97761
    },
    {
      "x": 0.94717,
      "y": 0.97855
    },
    {
      "x": 0.94591,
      "y": 0.9824
    },
    {
      "x": 0.9447,
      "y": 0.98624
    },
    {
      "x": 0.94402,
      "y": 0.98827
    },
    {
      "x": 0.94324,
      "y": 0.99036
    },
    {
      "x": 0.94286,
      "y": 0.99123
    },
    {
      "x": 0.9416,
      "y": 0.99386
    },
    {
      "x": 0.94101,
      "y": 0.99508
    },
    {
      "x": 0.94053,
      "y": 0.99589
    },
    {
      "x": 0.93922,
      "y": 0.9975
    },
    {
      "x": 0.93723,
      "y": 0.99912
    },
    {
      "x": 0.93442,
      "y": 1.0
    },
    {
      "x": 0.93437,
      "y": 1.0
    },
    {
      "x": 0.93122,
      "y": 0.99987
    },
    {
      "x": 0.93011,
      "y": 0.99966
    },
    {
      "x": 0.92875,
      "y": 0.99926
    },
    {
      "x": 0.92657,
      "y": 0.99845
    },
    {
      "x": 0.92381,
      "y": 0.9973
    },
    {
      "x": 0.92357,
      "y": 0.99723
    },
    {
      "x": 0.92153,
      "y": 0.99629
    },
    {
      "x": 0.9193,
      "y": 0.99514
    },
    {
      "x": 0.91799,
      "y": 0.99447
    },
    {
      "x": 0.91707,
      "y": 0.99393
    },
    {
      "x": 0.91411,
      "y": 0.99238
    },
    {
      "x": 0.91387,
      "y": 0.99224
    },
    {
      "x": 0.9114,
      "y": 0.9909
    },
    {
      "x": 0.91058,
      "y": 0.99042
    },
    {
      "x": 0.90791,
      "y": 0.98894
    },
    {
      "x": 0.90505,
      "y": 0.98739
    },
    {
      "x": 0.90229,
      "y": 0.98597
    },
    {
      "x": 0.89826,
      "y": 0.98388
    },
    {
      "x": 0.89444,
      "y": 0.98186
    },
    {
      "x": 0.89288,
      "y": 0.98112
    },
    {
      "x": 0.88964,
      "y": 0.9795
    },
    {
      "x": 0.88828,
      "y": 0.97882
    },
    {
      "x": 0.88149,
      "y": 0.97532
    },
    {
      "x": 0.87951,
      "y": 0.97431
    },
    {
      "x": 0.87742,
      "y": 0.97323
    },
    {
      "x": 0.87447,
      "y": 0.97168
    },
    {
      "x": 0.87117,
      "y": 0.96999
    },
    {
      "x": 0.86972,
      "y": 0.96925
    },
    {
      "x": 0.8638,
      "y": 0.96615
    },
    {
      "x": 0.856,
      "y": 0.9621
    },
    {
      "x": 0.8559,
      "y": 0.96203
    },
    {
      "x": 0.84951,
      "y": 0.95866
    },
    {
      "x": 0.845,
      "y": 0.95637
    },
    {
      "x": 0.84316,
      "y": 0.95542
    },
    {
      "x": 0.84257,
      "y": 0.95515
    },
    {
      "x": 0.83104,
      "y": 0.94902
    },
    {
      "x": 0.83046,
      "y": 0.94875
    },
    {
      "x": 0.82513,
      "y": 0.94591
    },
    {
      "x": 0.82236,
      "y": 0.9445
    },
    {
      "x": 0.81471,
      "y": 0.94052
    },
    {
      "x": 0.81466,
      "y": 0.94045
    },
    {
      "x": 0.80734,
      "y": 0.93667
    },
    {
      "x": 0.80559,
      "y": 0.9358
    },
    {
      "x": 0.79488,
      "y": 0.93013
    },
    {
      "x": 0.79033,
      "y": 0.92777
    },
    {
      "x": 0.78839,
      "y": 0.92669
    },
    {
      "x": 0.78402,
      "y": 0.9242
    },
    {
      "x": 0.78291,
      "y": 0.92366
    },
    {
      "x": 0.77467,
      "y": 0.919
    },
    {
      "x": 0.77336,
      "y": 0.9182
    },
    {
      "x": 0.76507,
      "y": 0.91327
    },
    {
      "x": 0.75397,
      "y": 0.90646
    },
    {
      "x": 0.7532,
      "y": 0.90606
    },
    {
      "x": 0.7468,
      "y": 0.90221
    },
    {
      "x": 0.74351,
      "y": 0.90019
    },
    {
      "x": 0.73454,
      "y": 0.89479
    },
    {
      "x": 0.73144,
      "y": 0.89297
    },
    {
      "x": 0.72649,
      "y": 0.88994
    },
    {
      "x": 0.71476,
      "y": 0.88292
    },
    {
      "x": 0.71379,
      "y": 0.88238
    },
    {
      "x": 0.70997,
      "y": 0.88009
    },
    {
      "x": 0.70793,
      "y": 0.87888
    },
    {
      "x": 0.70202,
      "y": 0.8753
    },
    {
      "x": 0.69596,
      "y": 0.87166
    },
    {
      "x": 0.68937,
      "y": 0.86775
    },
    {
      "x": 0.68859,
      "y": 0.86721
    },
    {
      "x": 0.68185,
      "y": 0.86323
    },
    {
      "x": 0.67512,
      "y": 0.85919
    },
    {
      "x": 0.67507,
      "y": 0.85912
    },
    {
      "x": 0.66828,
      "y": 0.85507
    },
    {
      "x": 0.66542,
      "y": 0.85332
    },
    {
      "x": 0.65709,
      "y": 0.84826
    },
    {
      "x": 0.65461,
      "y": 0.84678
    },
    {
      "x": 0.65132,
      "y": 0.84475
    },
    {
      "x": 0.64318,
      "y": 0.8397
    },
    {
      "x": 0.64308,
      "y": 0.83963
    },
    {
      "x": 0.62931,
      "y": 0.83106
    },
    {
      "x": 0.6218,
      "y": 0.82634
    },
    {
      "x": 0.61773,
      "y": 0.82391
    },
    {
      "x": 0.61075,
      "y": 0.8196
    },
    {
      "x": 0.60876,
      "y": 0.81832
    },
    {
      "x": 0.59975,
      "y": 0.81279
    },
    {
      "x": 0.59442,
      "y": 0.80941
    },
    {
      "x": 0.59311,
      "y": 0.80867
    },
    {
      "x": 0.58908,
      "y": 0.80618
    },
    {
      "x": 0.58618,
      "y": 0.80442
    },
    {
      "x": 0.58346,
      "y": 0.80267
    },
    {
      "x": 0.58051,
      "y": 0.80085
    },
    {
      "x": 0.57755,
      "y": 0.79903
    },
    {
      "x": 0.57571,
      "y": 0.79795
    },
    {
      "x": 0.57004,
      "y": 0.79438
    },
    {
      "x": 0.56853,
      "y": 0.79336
    },
    {
      "x": 0.56611,
      "y": 0.79188
    },
    {
      "x": 0.56577,
      "y": 0.79161
    },
    {
      "x": 0.56248,
      "y": 0.78945
    },
    {
      "x": 0.56185,
      "y": 0.78912
    },
    {
      "x": 0.55874,
      "y": 0.78702
    },
    {
      "x": 0.55816,
      "y": 0.78655
    },
    {
      "x": 0.55157,
      "y": 0.77988
    },
    {
      "x": 0.55123,
      "y": 0.77934
    },
    {
      "x": 0.54973,
      "y": 0.77644
    },
    {
      "x": 0.54924,
      "y": 0.77435
    },
    {
      "x": 0.54876,
      "y": 0.77097
    },
    {
      "x": 0.54886,
      "y": 0.76807
    },
    {
      "x": 0.54924,
      "y": 0.76598
    },
    {
      "x": 0.54944,
      "y": 0.76524
    },
    {
      "x": 0.55036,
      "y": 0.76146
    },
    {
      "x": 0.55046,
      "y": 0.76113
    },
    {
      "x": 0.55133,
      "y": 0.75843
    },
    {
      "x": 0.55167,
      "y": 0.75735
    },
    {
      "x": 0.55239,
      "y": 0.75533
    },
    {
      "x": 0.55307,
      "y": 0.75337
    },
    {
      "x": 0.55472,
      "y": 0.74892
    },
    {
      "x": 0.55506,
      "y": 0.74811
    },
    {
      "x": 0.55554,
      "y": 0.74676
    },
    {
      "x": 0.55792,
      "y": 0.73982
    },
    {
      "x": 0.5586,
      "y": 0.73752
    },
    {
      "x": 0.55942,
      "y": 0.73483
    },
    {
      "x": 0.56034,
      "y": 0.73085
    },
    {
      "x": 0.56088,
      "y": 0.72869
    },
    {
      "x": 0.56204,
      "y": 0.72377
    },
    {
      "x": 0.56296,
      "y": 0.71985
    },
    {
      "x": 0.56388,
      "y": 0.71547
    },
    {
      "x": 0.56432,
      "y": 0.71365
    },
    {
      "x": 0.56534,
      "y": 0.7096
    },
    {
      "x": 0.56713,
      "y": 0.70333
    },
    {
      "x": 0.5682,
      "y": 0.69949
    },
    {
      "x": 0.56975,
      "y": 0.6945
    },
    {
      "x": 0.57154,
      "y": 0.6891
    },
    {
      "x": 0.57173,
      "y": 0.68843
    },
    {
      "x": 0.57396,
      "y": 0.68189
    },
    {
      "x": 0.57508,
      "y": 0.67851
    },
    {
      "x": 0.57595,
      "y": 0.67602
    },
    {
      "x": 0.57706,
      "y": 0.67285
    },
    {
      "x": 0.5776,
      "y": 0.67103
    },
    {
      "x": 0.57871,
      "y": 0.66766
    },
    {
      "x": 0.57929,
      "y": 0.6657
    },
    {
      "x": 0.58017,
      "y": 0.66287
    },
    {
      "x": 0.58104,
      "y": 0.65983
    },
    {
      "x": 0.58196,
      "y": 0.65646
    },
    {
      "x": 0.58211,
      "y": 0.65606
    },
    {
      "x": 0.58278,
      "y": 0.65329
    },
    {
      "x": 0.58307,
      "y": 0.65214
    },
    {
      "x": 0.58351,
      "y": 0.64985
    },
    {
      "x": 0.5838,
      "y": 0.64837
    },
    {
      "x": 0.58424,
      "y": 0.64554
    },
    {
      "x": 0.58429,
      "y": 0.64486
    },
    {
      "x": 0.58448,
      "y": 0.64216
    },
    {
      "x": 0.58453,
      "y": 0.64149
    },
    {
      "x": 0.58448,
      "y": 0.63893
    },
    {
      "x": 0.58443,
      "y": 0.63859
    },
    {
      "x": 0.5839,
      "y": 0.63528
    },
    {
      "x": 0.5838,
      "y": 0.63495
    },
    {
      "x": 0.58191,
      "y": 0.63043
    },
    {
      "x": 0.58191,
      "y": 0.63043
    },
    {
      "x": 0.57988,
      "y": 0.62773
    },
    {
      "x": 0.57988,
      "y": 0.62773
    },
    {
      "x": 0.57551,
      "y": 0.62395
    },
    {
      "x": 0.57527,
      "y": 0.62375
    },
    {
      "x": 0.57285,
      "y": 0.6222
    },
    {
      "x": 0.57265,
      "y": 0.62207
    },
    {
      "x": 0.57013,
      "y": 0.62058
    },
    {
      "x": 0.5695,
      "y": 0.62018
    },
    {
      "x": 0.56761,
      "y": 0.61917
    },
    {
      "x": 0.56669,
      "y": 0.61863
    },
    {
      "x": 0.56369,
      "y": 0.61708
    },
    {
      "x": 0.56126,
      "y": 0.61586
    },
    {
      "x": 0.55695,
      "y": 0.6137
    },
    {
      "x": 0.55695,
      "y": 0.6137
    },
    {
      "x": 0.55395,
      "y": 0.61209
    },
    {
      "x": 0.5523,
      "y": 0.61121
    },
    {
      "x": 0.5507,
      "y": 0.61026
    },
    {
      "x": 0.54677,
      "y": 0.6079
    },
    {
      "x": 0.54469,
      "y": 0.60662
    },
    {
      "x": 0.5365,
      "y": 0.60156
    },
    {
      "x": 0.53601,
      "y": 0.60123
    },
    {
      "x": 0.53354,
      "y": 0.59974
    },
    {
      "x": 0.53218,
      "y": 0.59893
    },
    {
      "x": 0.52472,
      "y": 0.59469
    },
    {
      "x": 0.52467,
      "y": 0.59469
    },
    {
      "x": 0.519,
      "y": 0.59131
    },
    {
      "x": 0.51847,
      "y": 0.59098
    },
    {
      "x": 0.51435,
      "y": 0.58835
    },
    {
      "x": 0.5143,
      "y": 0.58835
    },
    {
      "x": 0.50693,
      "y": 0.58315
    },
    {
      "x": 0.50247,
      "y": 0.57971
    },
    {
      "x": 0.50111,
      "y": 0.57857
    },
    {
      "x": 0.49753,
      "y": 0.5756
    },
    {
      "x": 0.49258,
      "y": 0.57149
    },
    {
      "x": 0.4904,
      "y": 0.56967
    },
    {
      "x": 0.48764,
      "y": 0.56737
    },
    {
      "x": 0.48391,
      "y": 0.5642
    },
    {
      "x": 0.48231,
      "y": 0.56292
    },
    {
      "x": 0.47833,
      "y": 0.55962
    },
    {
      "x": 0.47305,
      "y": 0.5555
    },
    {
      "x": 0.47077,
      "y": 0.55382
    },
    {
      "x": 0.46864,
      "y": 0.5522
    },
    {
      "x": 0.46661,
      "y": 0.55071
    },
    {
      "x": 0.46336,
      "y": 0.54815
    },
    {
      "x": 0.4605,
      "y": 0.54579
    },
    {
      "x": 0.45725,
      "y": 0.54296
    },
    {
      "x": 0.45531,
      "y": 0.54114
    },
    {
      "x": 0.45197,
      "y": 0.53729
    },
    {
      "x": 0.45173,
      "y": 0.53702
    },
    {
      "x": 0.4494,
      "y": 0.53392
    },
    {
      "x": 0.44828,
      "y": 0.53217
    },
    {
      "x": 0.44644,
      "y": 0.52866
    },
    {
      "x": 0.44591,
      "y": 0.52731
    },
    {
      "x": 0.44431,
      "y": 0.52118
    },
    {
      "x": 0.44392,
      "y": 0.51942
    },
    {
      "x": 0.44407,
      "y": 0.5178
    },
    {
      "x": 0.44426,
      "y": 0.51652
    },
    {
      "x": 0.44533,
      "y": 0.50991
    },
    {
      "x": 0.44605,
      "y": 0.50769
    },
    {
      "x": 0.44635,
      "y": 0.50681
    },
    {
      "x": 0.44761,
      "y": 0.50337
    },
    {
      "x": 0.44833,
      "y": 0.50135
    },
    {
      "x": 0.44906,
      "y": 0.49912
    },
    {
      "x": 0.45008,
      "y": 0.49568
    },
    {
      "x": 0.45027,
      "y": 0.49487
    },
    {
      "x": 0.45076,
      "y": 0.49123
    },
    {
      "x": 0.45076,
      "y": 0.49083
    },
    {
      "x": 0.45076,
      "y": 0.48793
    },
    {
      "x": 0.45022,
      "y": 0.48617
    },
    {
      "x": 0.45008,
      "y": 0.4857
    },
    {
      "x": 0.44935,
      "y": 0.48381
    },
    {
      "x": 0.44916,
      "y": 0.48341
    },
    {
      "x": 0.44664,
      "y": 0.47957
    },
    {
      "x": 0.4461,
      "y": 0.47882
    },
    {
      "x": 0.44552,
      "y": 0.47822
    },
    {
      "x": 0.44504,
      "y": 0.47774
    },
    {
      "x": 0.44436,
      "y": 0.47707
    },
    {
      "x": 0.44193,
      "y": 0.47458
    },
    {
      "x": 0.44092,
      "y": 0.47363
    },
    {
      "x": 0.43917,
      "y": 0.47208
    },
    {
      "x": 0.4384,
      "y": 0.47141
    },
    {
      "x": 0.4368,
      "y": 0.47006
    },
    {
      "x": 0.43626,
      "y": 0.46965
    },
    {
      "x": 0.43428,
      "y": 0.4679
    },
    {
      "x": 0.43394,
      "y": 0.46763
    },
    {
      "x": 0.42798,
      "y": 0.46223
    },
    {
      "x": 0.4273,
      "y": 0.46156
    },
    {
      "x": 0.42565,
      "y": 0.46001
    },
    {
      "x": 0.42235,
      "y": 0.4565
    },
    {
      "x": 0.42182,
      "y": 0.45589
    },
    {
      "x": 0.41605,
      "y": 0.44949
    },
    {
      "x": 0.41358,
      "y": 0.44672
    },
    {
      "x": 0.41193,
      "y": 0.4449
    },
    {
      "x": 0.4097,
      "y": 0.44247
    },
    {
      "x": 0.40675,
      "y": 0.4393
    },
    {
      "x": 0.40558,
      "y": 0.43809
    },
    {
      "x": 0.40258,
      "y": 0.43492
    },
    {
      "x": 0.39788,
      "y": 0.43006
    },
    {
      "x": 0.39424,
      "y": 0.42629
    },
    {
      "x": 0.39221,
      "y": 0.42413
    },
    {
      "x": 0.39022,
      "y": 0.42204
    },
    {
      "x": 0.38833,
      "y": 0.42002
    },
    {
      "x": 0.38416,
      "y": 0.41563
    },
    {
      "x": 0.37878,
      "y": 0.40997
    },
    {
      "x": 0.37597,
      "y": 0.40693
    },
    {
      "x": 0.37466,
      "y": 0.40558
    },
    {
      "x": 0.37146,
      "y": 0.40221
    },
    {
      "x": 0.37103,
      "y": 0.40174
    },
    {
      "x": 0.35949,
      "y": 0.38953
    },
    {
      "x": 0.35886,
      "y": 0.38886
    },
    {
      "x": 0.35246,
      "y": 0.38205
    },
    {
      "x": 0.34907,
      "y": 0.37841
    },
    {
      "x": 0.34679,
      "y": 0.37598
    },
    {
      "x": 0.34112,
      "y": 0.37004
    },
    {
      "x": 0.33957,
      "y": 0.36842
    },
    {
      "x": 0.33564,
      "y": 0.36431
    },
    {
      "x": 0.33206,
      "y": 0.3606
    },
    {
      "x": 0.33162,
      "y": 0.3602
    },
    {
      "x": 0.3308,
      "y": 0.35932
    },
    {
      "x": 0.32532,
      "y": 0.35352
    },
    {
      "x": 0.32299,
      "y": 0.35096
    },
    {
      "x": 0.32023,
      "y": 0.34792
    },
    {
      "x": 0.31858,
      "y": 0.34603
    },
    {
      "x": 0.31834,
      "y": 0.34576
    },
    {
      "x": 0.31466,
      "y": 0.34152
    },
    {
      "x": 0.31374,
      "y": 0.3405
    },
    {
      "x": 0.31068,
      "y": 0.33733
    },
    {
      "x": 0.30952,
      "y": 0.33619
    },
    {
      "x": 0.30598,
      "y": 0.33309
    },
    {
      "x": 0.30564,
      "y": 0.33282
    },
    {
      "x": 0.30462,
      "y": 0.33214
    },
    {
      "x": 0.30365,
      "y": 0.3316
    },
    {
      "x": 0.30322,
      "y": 0.3314
    },
    {
      "x": 0.30181,
      "y": 0.33079
    },
    {
      "x": 0.30157,
      "y": 0.33079
    },
    {
      "x": 0.29895,
      "y": 0.33059
    },
    {
      "x": 0.29823,
      "y": 0.33073
    },
    {
      "x": 0.29595,
      "y": 0.33241
    },
    {
      "x": 0.29527,
      "y": 0.33322
    },
    {
      "x": 0.2944,
      "y": 0.33457
    },
    {
      "x": 0.29304,
      "y": 0.33707
    },
    {
      "x": 0.29294,
      "y": 0.33727
    },
    {
      "x": 0.29207,
      "y": 0.33949
    },
    {
      "x": 0.2912,
      "y": 0.34206
    },
    {
      "x": 0.29086,
      "y": 0.343
    },
    {
      "x": 0.29028,
      "y": 0.34496
    },
    {
      "x": 0.2897,
      "y": 0.34698
    },
    {
      "x": 0.28936,
      "y": 0.34813
    },
    {
      "x": 0.28863,
      "y": 0.35096
    },
    {
      "x": 0.28829,
      "y": 0.35244
    },
    {
      "x": 0.28756,
      "y": 0.35527
    },
    {
      "x": 0.28718,
      "y": 0.35716
    },
    {
      "x": 0.28596,
      "y": 0.36229
    },
    {
      "x": 0.28558,
      "y": 0.36424
    },
    {
      "x": 0.28461,
      "y": 0.36876
    },
    {
      "x": 0.28422,
      "y": 0.37085
    },
    {
      "x": 0.28335,
      "y": 0.3747
    },
    {
      "x": 0.28281,
      "y": 0.37746
    },
    {
      "x": 0.28228,
      "y": 0.37982
    },
    {
      "x": 0.28126,
      "y": 0.38481
    },
    {
      "x": 0.27971,
      "y": 0.39176
    },
    {
      "x": 0.27937,
      "y": 0.39338
    },
    {
      "x": 0.27782,
      "y": 0.40059
    },
    {
      "x": 0.277,
      "y": 0.4041
    },
    {
      "x": 0.27579,
      "y": 0.40963
    },
    {
      "x": 0.27549,
      "y": 0.41084
    },
    {
      "x": 0.27467,
      "y": 0.41489
    },
    {
      "x": 0.27438,
      "y": 0.41604
    },
    {
      "x": 0.27283,
      "y": 0.42319
    },
    {
      "x": 0.27283,
      "y": 0.42325
    },
    {
      "x": 0.272,
      "y": 0.42723
    },
    {
      "x": 0.27123,
      "y": 0.43087
    },
    {
      "x": 0.27084,
      "y": 0.43283
    },
    {
      "x": 0.2705,
      "y": 0.43418
    },
    {
      "x": 0.26987,
      "y": 0.43742
    },
    {
      "x": 0.26963,
      "y": 0.43829
    },
    {
      "x": 0.26842,
      "y": 0.44409
    },
    {
      "x": 0.26808,
      "y": 0.44544
    },
    {
      "x": 0.26764,
      "y": 0.44767
    },
    {
      "x": 0.26711,
      "y": 0.44976
    },
    {
      "x": 0.26662,
      "y": 0.45144
    },
    {
      "x": 0.26493,
      "y": 0.45637
    },
    {
      "x": 0.26454,
      "y": 0.45724
    },
    {
      "x": 0.26241,
      "y": 0.45886
    },
    {
      "x": 0.26183,
      "y": 0.45913
    },
    {
      "x": 0.25775,
      "y": 0.46169
    },
    {
      "x": 0.25674,
      "y": 0.4623
    },
    {
      "x": 0.25519,
      "y": 0.46331
    },
    {
      "x": 0.25364,
      "y": 0.46405
    },
    {
      "x": 0.25315,
      "y": 0.46432
    },
    {
      "x": 0.24855,
      "y": 0.46648
    },
    {
      "x": 0.24855,
      "y": 0.46655
    },
    {
      "x": 0.24535,
      "y": 0.46756
    },
    {
      "x": 0.24496,
      "y": 0.4677
    },
    {
      "x": 0.2421,
      "y": 0.4683
    },
    {
      "x": 0.239,
      "y": 0.46878
    },
    {
      "x": 0.23764,
      "y": 0.46898
    },
    {
      "x": 0.2359,
      "y": 0.46911
    },
    {
      "x": 0.23144,
      "y": 0.46958
    },
    {
      "x": 0.23115,
      "y": 0.46965
    },
    {
      "x": 0.22882,
      "y": 0.46999
    },
    {
      "x": 0.22829,
      "y": 0.47012
    },
    {
      "x": 0.2264,
      "y": 0.47046
    },
    {
      "x": 0.22509,
      "y": 0.47087
    },
    {
      "x": 0.22358,
      "y": 0.47134
    },
    {
      "x": 0.2231,
      "y": 0.47161
    },
    {
      "x": 0.22092,
      "y": 0.47262
    },
    {
      "x": 0.21816,
      "y": 0.47451
    },
    {
      "x": 0.21791,
      "y": 0.47471
    },
    {
      "x": 0.21535,
      "y": 0.47761
    },
    {
      "x": 0.21408,
      "y": 0.47936
    },
    {
      "x": 0.2136,
      "y": 0.48078
    },
    {
      "x": 0.21336,
      "y": 0.48159
    },
    {
      "x": 0.21258,
      "y": 0.4853
    },
    {
      "x": 0.21224,
      "y": 0.48746
    },
    {
      "x": 0.21205,
      "y": 0.49117
    },
    {
      "x": 0.21205,
      "y": 0.49508
    },
    {
      "x": 0.21181,
      "y": 0.49933
    },
    {
      "x": 0.21181,
      "y": 0.49939
    },
    {
      "x": 0.2104,
      "y": 0.50465
    },
    {
      "x": 0.21016,
      "y": 0.50533
    },
    {
      "x": 0.20846,
      "y": 0.50708
    },
    {
      "x": 0.20778,
      "y": 0.50755
    },
    {
      "x": 0.20507,
      "y": 0.50877
    },
    {
      "x": 0.20478,
      "y": 0.50883
    },
    {
      "x": 0.20211,
      "y": 0.50931
    },
    {
      "x": 0.20153,
      "y": 0.50937
    },
    {
      "x": 0.19906,
      "y": 0.50944
    },
    {
      "x": 0.19746,
      "y": 0.50937
    },
    {
      "x": 0.19572,
      "y": 0.50924
    },
    {
      "x": 0.19329,
      "y": 0.5089
    },
    {
      "x": 0.19295,
      "y": 0.5089
    },
    {
      "x": 0.18985,
      "y": 0.50836
    },
    {
      "x": 0.18922,
      "y": 0.50823
    },
    {
      "x": 0.18505,
      "y": 0.50728
    },
    {
      "x": 0.18258,
      "y": 0.50647
    },
    {
      "x": 0.18064,
      "y": 0.5058
    },
    {
      "x": 0.17793,
      "y": 0.50465
    },
    {
      "x": 0.17284,
      "y": 0.50202
    },
    {
      "x": 0.16407,
      "y": 0.49697
    },
    {
      "x": 0.16159,
      "y": 0.49548
    },
    {
      "x": 0.15835,
      "y": 0.49326
    },
    {
      "x": 0.15796,
      "y": 0.49299
    },
    {
      "x": 0.15471,
      "y": 0.49103
    },
    {
      "x": 0.15282,
      "y": 0.48988
    },
    {
      "x": 0.15001,
      "y": 0.4882
    },
    {
      "x": 0.14904,
      "y": 0.48766
    },
    {
      "x": 0.1456,
      "y": 0.4857
    },
    {
      "x": 0.14405,
      "y": 0.48483
    },
    {
      "x": 0.13998,
      "y": 0.48247
    },
    {
      "x": 0.13857,
      "y": 0.48159
    },
    {
      "x": 0.13532,
      "y": 0.47957
    },
    {
      "x": 0.133,
      "y": 0.47801
    },
    {
      "x": 0.12524,
      "y": 0.47262
    },
    {
      "x": 0.12519,
      "y": 0.47262
    },
    {
      "x": 0.12156,
      "y": 0.46999
    },
    {
      "x": 0.11836,
      "y": 0.46763
    },
    {
      "x": 0.11836,
      "y": 0.46763
    },
    {
      "x": 0.11414,
      "y": 0.46459
    },
    {
      "x": 0.11007,
      "y": 0.46169
    },
    {
      "x": 0.10838,
      "y": 0.46055
    },
    {
      "x": 0.10615,
      "y": 0.45906
    },
    {
      "x": 0.10266,
      "y": 0.45664
    },
    {
      "x": 0.10154,
      "y": 0.45589
    },
    {
      "x": 0.09577,
      "y": 0.45192
    },
    {
      "x": 0.09262,
      "y": 0.44962
    },
    {
      "x": 0.0855,
      "y": 0.44429
    },
    {
      "x": 0.08288,
      "y": 0.44234
    },
    {
      "x": 0.07954,
      "y": 0.43978
    },
    {
      "x": 0.07813,
      "y": 0.43863
    },
    {
      "x": 0.07614,
      "y": 0.43701
    },
    {
      "x": 0.0711,
      "y": 0.4329
    },
    {
      "x": 0.06989,
      "y": 0.43189
    },
    {
      "x": 0.06446,
      "y": 0.4275
    },
    {
      "x": 0.06262,
      "y": 0.42602
    },
    {
      "x": 0.05962,
      "y": 0.42359
    },
    {
      "x": 0.05404,
      "y": 0.41934
    },
    {
      "x": 0.04915,
      "y": 0.41563
    },
    {
      "x": 0.04668,
      "y": 0.41381
    },
    {
      "x": 0.04251,
      "y": 0.41051
    },
    {
      "x": 0.04071,
      "y": 0.40896
    },
    {
      "x": 0.0394,
      "y": 0.40761
    },
    {
      "x": 0.03034,
      "y": 0.39358
    },
    {
      "x": 0.02908,
      "y": 0.39122
    },
    {
      "x": 0.02734,
      "y": 0.38717
    },
    {
      "x": 0.02608,
      "y": 0.38272
    },
    {
      "x": 0.02608,
      "y": 0.38265
    },
    {
      "x": 0.02399,
      "y": 0.3751
    },
    {
      "x": 0.02312,
      "y": 0.37186
    },
    {
      "x": 0.01881,
      "y": 0.35298
    },
    {
      "x": 0.01822,
      "y": 0.35028
    },
    {
      "x": 0.01454,
      "y": 0.33282
    },
    {
      "x": 0.01435,
      "y": 0.33174
    },
    {
      "x": 0.01217,
      "y": 0.32196
    },
    {
      "x": 0.01076,
      "y": 0.31623
    },
    {
      "x": 0.01037,
      "y": 0.31461
    },
    {
      "x": 0.00795,
      "y": 0.30449
    },
    {
      "x": 0.00771,
      "y": 0.30341
    },
    {
      "x": 0.00475,
      "y": 0.28999
    },
    {
      "x": 0.00475,
      "y": 0.28992
    },
    {
      "x": 0.00315,
      "y": 0.28156
    },
    {
      "x": 0.00204,
      "y": 0.27408
    },
    {
      "x": 0.00165,
      "y": 0.27131
    },
    {
      "x": 0.0,
      "y": 0.23732
    },
    {
      "x": 0.0001,
      "y": 0.23449
    },
    {
      "x": 0.00058,
      "y": 0.22181
    },
    {
      "x": 0.00107,
      "y": 0.21244
    },
    {
      "x": 0.00184,
      "y": 0.19719
    },
    {
      "x": 0.00194,
      "y": 0.19551
    },
    {
      "x": 0.00252,
      "y": 0.18654
    },
    {
      "x": 0.00252,
      "y": 0.1858
    },
    {
      "x": 0.0031,
      "y": 0.17622
    },
    {
      "x": 0.00315,
      "y": 0.17615
    },
    {
      "x": 0.00354,
      "y": 0.1684
    },
    {
      "x": 0.00368,
      "y": 0.16543
    },
    {
      "x": 0.00373,
      "y": 0.16125
    },
    {
      "x": 0.00364,
      "y": 0.15397
    },
    {
      "x": 0.00354,
      "y": 0.15113
    },
    {
      "x": 0.00339,
      "y": 0.14844
    },
    {
      "x": 0.00305,
      "y": 0.14311
    },
    {
      "x": 0.00301,
      "y": 0.14196
    },
    {
      "x": 0.00267,
      "y": 0.13717
    },
    {
      "x": 0.00247,
      "y": 0.13373
    },
    {
      "x": 0.00228,
      "y": 0.13144
    },
    {
      "x": 0.00208,
      "y": 0.12753
    },
    {
      "x": 0.00204,
      "y": 0.12706
    },
    {
      "x": 0.00184,
      "y": 0.11917
    },
    {
      "x": 0.00179,
      "y": 0.11876
    },
    {
      "x": 0.00179,
      "y": 0.11512
    },
    {
      "x": 0.00179,
      "y": 0.11485
    },
    {
      "x": 0.00199,
      "y": 0.11256
    },
    {
      "x": 0.00204,
      "y": 0.11155
    },
    {
      "x": 0.00247,
      "y": 0.10878
    },
    {
      "x": 0.00296,
      "y": 0.10682
    },
    {
      "x": 0.0033,
      "y": 0.10608
    },
    {
      "x": 0.00407,
      "y": 0.1044
    },
    {
      "x": 0.00519,
      "y": 0.10291
    },
    {
      "x": 0.00528,
      "y": 0.10271
    },
    {
      "x": 0.0063,
      "y": 0.10163
    },
    {
      "x": 0.00775,
      "y": 0.10049
    },
    {
      "x": 0.00863,
      "y": 0.09995
    },
    {
      "x": 0.0111,
      "y": 0.09826
    },
    {
      "x": 0.01299,
      "y": 0.09705
    },
    {
      "x": 0.01386,
      "y": 0.09637
    },
    {
      "x": 0.01473,
      "y": 0.09576
    },
    {
      "x": 0.01696,
      "y": 0.09415
    },
    {
      "x": 0.0173,
      "y": 0.09394
    },
    {
      "x": 0.01982,
      "y": 0.09219
    },
    {
      "x": 0.02002,
      "y": 0.09199
    },
    {
      "x": 0.02263,
      "y": 0.09003
    },
    {
      "x": 0.02443,
      "y": 0.08875
    },
    {
      "x": 0.02612,
      "y": 0.08747
    },
    {
      "x": 0.03364,
      "y": 0.08207
    },
    {
      "x": 0.03451,
      "y": 0.08153
    },
    {
      "x": 0.03674,
      "y": 0.07992
    },
    {
      "x": 0.0396,
      "y": 0.07789
    },
    {
      "x": 0.04517,
      "y": 0.07405
    },
    {
      "x": 0.04522,
      "y": 0.07405
    },
    {
      "x": 0.04968,
      "y": 0.07095
    },
    {
      "x": 0.04973,
      "y": 0.07095
    },
    {
      "x": 0.05395,
      "y": 0.06805
    },
    {
      "x": 0.05777,
      "y": 0.06535
    },
    {
      "x": 0.05836,
      "y": 0.06501
    },
    {
      "x": 0.06412,
      "y": 0.06076
    },
    {
      "x": 0.06417,
      "y": 0.06076
    },
    {
      "x": 0.06897,
      "y": 0.05719
    },
    {
      "x": 0.07115,
      "y": 0.05544
    },
    {
      "x": 0.07673,
      "y": 0.05112
    },
    {
      "x": 0.07847,
      "y": 0.04964
    },
    {
      "x": 0.08177,
      "y": 0.04694
    },
    {
      "x": 0.08463,
      "y": 0.04458
    },
    {
      "x": 0.08753,
      "y": 0.04215
    },
    {
      "x": 0.08996,
      "y": 0.04026
    },
    {
      "x": 0.0964,
      "y": 0.03514
    },
    {
      "x": 0.09912,
      "y": 0.03311
    },
    {
      "x": 0.10159,
      "y": 0.03136
    },
    {
      "x": 0.10164,
      "y": 0.03136
    },
    {
      "x": 0.10915,
      "y": 0.02596
    },
    {
      "x": 0.11191,
      "y": 0.02401
    },
    {
      "x": 0.11405,
      "y": 0.02232
    },
    {
      "x": 0.11783,
      "y": 0.01942
    },
    {
      "x": 0.12432,
      "y": 0.01409
    },
    {
      "x": 0.12481,
      "y": 0.01376
    },
    {
      "x": 0.12781,
      "y": 0.01133
    },
    {
      "x": 0.12922,
      "y": 0.01018
    },
    {
      "x": 0.13261,
      "y": 0.00769
    },
    {
      "x": 0.13266,
      "y": 0.00769
    },
    {
      "x": 0.13867,
      "y": 0.00384
    },
    {
      "x": 0.13906,
      "y": 0.00364
    },
    {
      "x": 0.14182,
      "y": 0.00229
    },
    {
      "x": 0.14303,
      "y": 0.00182
    },
    {
      "x": 0.14725,
      "y": 0.00067
    },
    {
      "x": 0.14909,
      "y": 0.0002
    },
    {
      "x": 0.152,
      "y": 0.0
    },
    {
      "x": 0.15418,
      "y": 0.00054
    },
    {
      "x": 0.15476,
      "y": 0.00074
    },
    {
      "x": 0.15747,
      "y": 0.00209
    },
    {
      "x": 0.15752,
      "y": 0.00216
    },
    {
      "x": 0.1597,
      "y": 0.00398
    },
    {
      "x": 0.16135,
      "y": 0.006
    },
    {
      "x": 0.16174,
      "y": 0.00654
    },
    {
      "x": 0.16305,
      "y": 0.00863
    },
    {
      "x": 0.16397,
      "y": 0.01025
    },
    {
      "x": 0.16523,
      "y": 0.01261
    },
    {
      "x": 0.16634,
      "y": 0.01524
    },
    {
      "x": 0.16925,
      "y": 0.02286
    },
    {
      "x": 0.1693,
      "y": 0.02293
    },
    {
      "x": 0.17061,
      "y": 0.0265
    },
    {
      "x": 0.1709,
      "y": 0.02731
    },
    {
      "x": 0.17269,
      "y": 0.0323
    },
    {
      "x": 0.17318,
      "y": 0.03359
    },
    {
      "x": 0.17492,
      "y": 0.03851
    },
    {
      "x": 0.1757,
      "y": 0.04073
    },
    {
      "x": 0.17686,
      "y": 0.0439
    },
    {
      "x": 0.17895,
      "y": 0.04977
    },
    {
      "x": 0.17982,
      "y": 0.0522
    },
    {
      "x": 0.18171,
      "y": 0.0578
    },
    {
      "x": 0.182,
      "y": 0.05854
    },
    {
      "x": 0.1835,
      "y": 0.06299
    },
    {
      "x": 0.18486,
      "y": 0.0669
    },
    {
      "x": 0.1852,
      "y": 0.06778
    },
    {
      "x": 0.1899,
      "y": 0.08086
    },
    {
      "x": 0.19034,
      "y": 0.08214
    },
    {
      "x": 0.19179,
      "y": 0.08612
    },
    {
      "x": 0.19266,
      "y": 0.08821
    },
    {
      "x": 0.19528,
      "y": 0.09442
    },
    {
      "x": 0.19722,
      "y": 0.0988
    },
    {
      "x": 0.19838,
      "y": 0.10143
    },
    {
      "x": 0.20265,
      "y": 0.1106
    },
    {
      "x": 0.20522,
      "y": 0.11552
    },
    {
      "x": 0.20749,
      "y": 0.11971
    },
    {
      "x": 0.21098,
      "y": 0.12584
    },
    {
      "x": 0.21215,
      "y": 0.1278
    },
    {
      "x": 0.21985,
      "y": 0.13899
    },
    {
      "x": 0.22039,
      "y": 0.13967
    },
    {
      "x": 0.22504,
      "y": 0.14567
    },
    {
      "x": 0.22863,
      "y": 0.15012
    },
    {
      "x": 0.22979,
      "y": 0.15154
    },
    {
      "x": 0.23173,
      "y": 0.1539
    },
    {
      "x": 0.23556,
      "y": 0.15842
    },
    {
      "x": 0.23565,
      "y": 0.15855
    },
    {
      "x": 0.24026,
      "y": 0.16408
    },
    {
      "x": 0.24414,
      "y": 0.1688
    },
    {
      "x": 0.24816,
      "y": 0.17386
    },
    {
      "x": 0.2533,
      "y": 0.18067
    },
    {
      "x": 0.25475,
      "y": 0.18276
    },
    {
      "x": 0.26207,
      "y": 0.19382
    },
    {
      "x": 0.26313,
      "y": 0.19544
    },
    {
      "x": 0.2673,
      "y": 0.20151
    },
    {
      "x": 0.26924,
      "y": 0.20401
    },
    {
      "x": 0.27399,
      "y": 0.21001
    },
    {
      "x": 0.28058,
      "y": 0.21864
    },
    {
      "x": 0.2849,
      "y": 0.22538
    },
    {
      "x": 0.28713,
      "y": 0.23044
    },
    {
      "x": 0.29066,
      "y": 0.23982
    },
    {
      "x": 0.29091,
      "y": 0.24063
    },
    {
      "x": 0.2927,
      "y": 0.24649
    },
    {
      "x": 0.29377,
      "y": 0.25061
    },
    {
      "x": 0.29716,
      "y": 0.26652
    },
    {
      "x": 0.2976,
      "y": 0.26868
    },
    {
      "x": 0.29861,
      "y": 0.27401
    },
    {
      "x": 0.29915,
      "y": 0.27806
    },
    {
      "x": 0.29973,
      "y": 0.28176
    },
    {
      "x": 0.30104,
      "y": 0.29053
    },
    {
      "x": 0.30109,
      "y": 0.29067
    },
    {
      "x": 0.30239,
      "y": 0.29883
    },
    {
      "x": 0.30244,
      "y": 0.29896
    },
    {
      "x": 0.30448,
      "y": 0.30901
    },
    {
      "x": 0.30467,
      "y": 0.30982
    },
    {
      "x": 0.30763,
      "y": 0.31919
    },
    {
      "x": 0.31039,
      "y": 0.32547
    },
    {
      "x": 0.31422,
      "y": 0.33214
    },
    {
      "x": 0.31466,
      "y": 0.33282
    },
    {
      "x": 0.3163,
      "y": 0.33518
    },
    {
      "x": 0.32086,
      "y": 0.34104
    },
    {
      "x": 0.3259,
      "y": 0.34664
    },
    {
      "x": 0.32745,
      "y": 0.34826
    },
    {
      "x": 0.33564,
      "y": 0.35642
    },
    {
      "x": 0.33947,
      "y": 0.3602
    },
    {
      "x": 0.34335,
      "y": 0.36418
    },
    {
      "x": 0.34456,
      "y": 0.36539
    },
    {
      "x": 0.35576,
      "y": 0.37739
    },
    {
      "x": 0.35585,
      "y": 0.37753
    },
    {
      "x": 0.36114,
      "y": 0.38319
    },
    {
      "x": 0.36628,
      "y": 0.38872
    },
    {
      "x": 0.36768,
      "y": 0.39021
    },
    {
      "x": 0.37195,
      "y": 0.39473
    },
    {
      "x": 0.37917,
      "y": 0.40235
    },
    {
      "x": 0.38023,
      "y": 0.40349
    },
    {
      "x": 0.3894,
      "y": 0.41327
    },
    {
      "x": 0.394,
      "y": 0.41813
    },
    {
      "x": 0.39909,
      "y": 0.42346
    },
    {
      "x": 0.4004,
      "y": 0.4248
    },
    {
      "x": 0.40495,
      "y": 0.42966
    },
    {
      "x": 0.41077,
      "y": 0.4358
    },
    {
      "x": 0.41213,
      "y": 0.43721
    },
    {
      "x": 0.42255,
      "y": 0.44854
    },
    {
      "x": 0.42308,
      "y": 0.44915
    },
    {
      "x": 0.42962,
      "y": 0.45589
    },
    {
      "x": 0.43273,
      "y": 0.45886
    },
    {
      "x": 0.43849,
      "y": 0.46399
    },
    {
      "x": 0.44164,
      "y": 0.46655
    },
    {
      "x": 0.45076,
      "y": 0.47296
    },
    {
      "x": 0.4509,
      "y": 0.47309
    },
    {
      "x": 0.46384,
      "y": 0.48071
    },
    {
      "x": 0.46801,
      "y": 0.48307
    },
    {
      "x": 0.47703,
      "y": 0.48793
    },
    {
      "x": 0.47712,
      "y": 0.488
    },
    {
      "x": 0.48115,
      "y": 0.49022
    },
    {
      "x": 0.48594,
      "y": 0.49292
    },
    {
      "x": 0.49021,
      "y": 0.49528
    },
    {
      "x": 0.49351,
      "y": 0.49717
    },
    {
      "x": 0.50102,
      "y": 0.50135
    },
    {
      "x": 0.50746,
      "y": 0.50499
    },
    {
      "x": 0.51032,
      "y": 0.50661
    },
    {
      "x": 0.52021,
      "y": 0.51221
    },
    {
      "x": 0.52506,
      "y": 0.51497
    },
    {
      "x": 0.52816,
      "y": 0.51673
    },
    {
      "x": 0.53926,
      "y": 0.5232
    },
    {
      "x": 0.5427,
      "y": 0.52516
    },
    {
      "x": 0.54406,
      "y": 0.52596
    },
    {
      "x": 0.54672,
      "y": 0.52745
    },
    {
      "x": 0.5523,
      "y": 0.53069
    },
    {
      "x": 0.56471,
      "y": 0.5379
    },
    {
      "x": 0.56698,
      "y": 0.53918
    },
    {
      "x": 0.56931,
      "y": 0.54053
    },
    {
      "x": 0.57168,
      "y": 0.54188
    },
    {
      "x": 0.57614,
      "y": 0.54444
    },
    {
      "x": 0.58031,
      "y": 0.54687
    },
    {
      "x": 0.58603,
      "y": 0.55024
    },
    {
      "x": 0.59214,
      "y": 0.55382
    },
    {
      "x": 0.59282,
      "y": 0.55422
    },
    {
      "x": 0.59999,
      "y": 0.55847
    },
    {
      "x": 0.60222,
      "y": 0.55975
    },
    {
      "x": 0.60624,
      "y": 0.56218
    },
    {
      "x": 0.60847,
      "y": 0.56346
    },
    {
      "x": 0.61254,
      "y": 0.56589
    },
    {
      "x": 0.61792,
      "y": 0.56899
    },
    {
      "x": 0.625,
      "y": 0.57317
    },
    {
      "x": 0.62742,
      "y": 0.57459
    },
    {
      "x": 0.6361,
      "y": 0.57971
    },
    {
      "x": 0.63692,
      "y": 0.58019
    },
    {
      "x": 0.64424,
      "y": 0.5845
    },
    {
      "x": 0.65621,
      "y": 0.59152
    },
    {
      "x": 0.65694,
      "y": 0.59192
    },
    {
      "x": 0.66276,
      "y": 0.59536
    },
    {
      "x": 0.66833,
      "y": 0.59866
    },
    {
      "x": 0.67143,
      "y": 0.60049
    },
    {
      "x": 0.67579,
      "y": 0.60305
    },
    {
      "x": 0.68171,
      "y": 0.60656
    },
    {
      "x": 0.6852,
      "y": 0.60858
    },
    {
      "x": 0.69087,
      "y": 0.61195
    },
    {
      "x": 0.69097,
      "y": 0.61202
    },
    {
      "x": 0.69819,
      "y": 0.61627
    },
    {
      "x": 0.69911,
      "y": 0.61681
    },
    {
      "x": 0.70565,
      "y": 0.62072
    },
    {
      "x": 0.7088,
      "y": 0.62254
    },
    {
      "x": 0.71699,
      "y": 0.62726
    },
    {
      "x": 0.71709,
      "y": 0.62733
    },
    {
      "x": 0.72358,
      "y": 0.63104
    },
    {
      "x": 0.73066,
      "y": 0.63495
    },
    {
      "x": 0.74021,
      "y": 0.63994
    },
    {
      "x": 0.74113,
      "y": 0.64048
    },
    {
      "x": 0.75223,
      "y": 0.64607
    },
    {
      "x": 0.75533,
      "y": 0.64769
    },
    {
      "x": 0.76047,
      "y": 0.65039
    },
    {
      "x": 0.76372,
      "y": 0.65208
    },
    {
      "x": 0.76706,
      "y": 0.65383
    },
    {
      "x": 0.77312,
      "y": 0.657
    },
    {
      "x": 0.78126,
      "y": 0.66125
    },
    {
      "x": 0.78524,
      "y": 0.66334
    },
    {
      "x": 0.79299,
      "y": 0.66739
    },
    {
      "x": 0.80264,
      "y": 0.67231
    },
    {
      "x": 0.80811,
      "y": 0.67514
    },
    {
      "x": 0.81146,
      "y": 0.6769
    },
    {
      "x": 0.81238,
      "y": 0.67743
    },
    {
      "x": 0.81975,
      "y": 0.68135
    },
    {
      "x": 0.8228,
      "y": 0.6831
    },
    {
      "x": 0.83613,
      "y": 0.69086
    },
    {
      "x": 0.83792,
      "y": 0.69187
    },
    {
      "x": 0.84509,
      "y": 0.69625
    },
    {
      "x": 0.85057,
      "y": 0.69942
    },
    {
      "x": 0.86521,
      "y": 0.70792
    },
    {
      "x": 0.86618,
      "y": 0.70846
    },
    {
      "x": 0.8766,
      "y": 0.71459
    }
  ],
  "sectors": [
    {
      "sector": 1,
      "start_index": 0,
      "end_index": 297,
      "start_dist": 0.0,
      "end_dist": 0.33333
    },
    {
      "sector": 2,
      "start_index": 298,
      "end_index": 625,
      "start_dist": 0.33333,
      "end_dist": 0.66667
    },
    {
      "sector": 3,
      "start_index": 626,
      "end_index": 836,
      "start_dist": 0.66667,
      "end_dist": 1.0
    }
  ]
}