{
  "circuit_key": 15,
  "name": "Catalunya",
  "short_name": "Catalunya",
  "location": "Barcelona",
  "country": "Spain",
  "source": "multiviewer",
  "source_url": "https://api.multiviewer.app/api/v1/circuits/15/2026",
  "bounds": {
    "min_x": -6741,
    "max_x": 2882,
    "min_y": -7453,
    "max_y": 4136
  },
  "points": [
    {
      "x": 0.84433,
      "y": 0.6224
    },
    {
      "x": 0.83841,
      "y": 0.61481
    },
    {
      "x": 0.82989,
      "y": 0.60359
    },
    {
      "x": 0.82459,
      "y": 0.59669
    },
    {
      "x": 0.81586,
      "y": 0.5853
    },
    {
      "x": 0.81045,
      "y": 0.57822
    },
    {
      "x": 0.79882,
      "y": 0.56312
    },
    {
      "x": 0.79196,
      "y": 0.55406
    },
    {
      "x": 0.78354,
      "y": 0.5431
    },
    {
      "x": 0.77585,
      "y": 0.53301
    },
    {
      "x": 0.76733,
      "y": 0.52187
    },
    {
      "x": 0.75517,
      "y": 0.506
    },
    {
      "x": 0.74509,
      "y": 0.49279
    },
    {
      "x": 0.73636,
      "y": 0.4814
    },
    {
      "x": 0.72909,
      "y": 0.47191
    },
    {
      "x": 0.72254,
      "y": 0.46328
    },
    {
      "x": 0.71662,
      "y": 0.45552
    },
    {
      "x": 0.70997,
      "y": 0.4468
    },
    {
      "x": 0.69968,
      "y": 0.43326
    },
    {
      "x": 0.69355,
      "y": 0.42549
    },
    {
      "x": 0.68004,
      "y": 0.40823
    },
    {
      "x": 0.67141,
      "y": 0.39745
    },
    {
      "x": 0.65489,
      "y": 0.37674
    },
    {
      "x": 0.64377,
      "y": 0.36284
    },
    {
      "x": 0.63816,
      "y": 0.35585
    },
    {
      "x": 0.63016,
      "y": 0.34593
    },
    {
      "x": 0.62039,
      "y": 0.33385
    },
    {
      "x": 0.61311,
      "y": 0.32479
    },
    {
      "x": 0.6049,
      "y": 0.31461
    },
    {
      "x": 0.59503,
      "y": 0.30236
    },
    {
      "x": 0.58755,
      "y": 0.29321
    },
    {
      "x": 0.57591,
      "y": 0.2788
    },
    {
      "x": 0.56417,
      "y": 0.2643
    },
    {
      "x": 0.55575,
      "y": 0.25386
    },
    {
      "x": 0.549,
      "y": 0.24558
    },
    {
      "x": 0.53944,
      "y": 0.23376
    },
    {
      "x": 0.53403,
      "y": 0.22694
    },
    {
      "x": 0.51522,
      "y": 0.20235
    },
    {
      "x": 0.51044,
      "y": 0.19579
    },
    {
      "x": 0.50109,
      "y": 0.1825
    },
    {
      "x": 0.49454,
      "y": 0.1731
    },
    {
      "x": 0.48197,
      "y": 0.15472
    },
    {
      "x": 0.47709,
      "y": 0.14738
    },
    {
      "x": 0.46784,
      "y": 0.13349
    },
    {
      "x": 0.46243,
      "y": 0.12538
    },
    {
      "x": 0.45516,
      "y": 0.11468
    },
    {
      "x": 0.44664,
      "y": 0.10251
    },
    {
      "x": 0.44217,
      "y": 0.09656
    },
    {
      "x": 0.43271,
      "y": 0.08456
    },
    {
      "x": 0.42835,
      "y": 0.07939
    },
    {
      "x": 0.42346,
      "y": 0.07404
    },
    {
      "x": 0.41609,
      "y": 0.06653
    },
    {
      "x": 0.41079,
      "y": 0.06161
    },
    {
      "x": 0.40445,
      "y": 0.05635
    },
    {
      "x": 0.40019,
      "y": 0.05315
    },
    {
      "x": 0.39624,
      "y": 0.05048
    },
    {
      "x": 0.39052,
      "y": 0.0472
    },
    {
      "x": 0.37805,
      "y": 0.04194
    },
    {
      "x": 0.37296,
      "y": 0.04064
    },
    {
      "x": 0.36943,
      "y": 0.04012
    },
    {
      "x": 0.35405,
      "y": 0.04021
    },
    {
      "x": 0.34605,
      "y": 0.04168
    },
    {
      "x": 0.34095,
      "y": 0.04314
    },
    {
      "x": 0.33763,
      "y": 0.04418
    },
    {
      "x": 0.33098,
      "y": 0.0466
    },
    {
      "x": 0.32204,
      "y": 0.04996
    },
    {
      "x": 0.31633,
      "y": 0.0522
    },
    {
      "x": 0.30812,
      "y": 0.05505
    },
    {
      "x": 0.30282,
      "y": 0.05661
    },
    {
      "x": 0.29804,
      "y": 0.05773
    },
    {
      "x": 0.29066,
      "y": 0.05876
    },
    {
      "x": 0.28567,
      "y": 0.05902
    },
    {
      "x": 0.27642,
      "y": 0.05833
    },
    {
      "x": 0.26468,
      "y": 0.05574
    },
    {
      "x": 0.25314,
      "y": 0.05186
    },
    {
      "x": 0.24566,
      "y": 0.04867
    },
    {
      "x": 0.23735,
      "y": 0.04452
    },
    {
      "x": 0.23007,
      "y": 0.04064
    },
    {
      "x": 0.22218,
      "y": 0.03598
    },
    {
      "x": 0.21594,
      "y": 0.03227
    },
    {
      "x": 0.2042,
      "y": 0.02554
    },
    {
      "x": 0.19027,
      "y": 0.01821
    },
    {
      "x": 0.18144,
      "y": 0.01407
    },
    {
      "x": 0.17188,
      "y": 0.01001
    },
    {
      "x": 0.16076,
      "y": 0.00613
    },
    {
      "x": 0.14434,
      "y": 0.00216
    },
    {
      "x": 0.13468,
      "y": 0.00078
    },
    {
      "x": 0.12657,
      "y": 9e-05
    },
    {
      "x": 0.11992,
      "y": 0.0
    },
    {
      "x": 0.10589,
      "y": 0.0006
    },
    {
      "x": 0.09716,
      "y": 0.00173
    },
    {
      "x": 0.08615,
      "y": 0.00388
    },
    {
      "x": 0.08002,
      "y": 0.00544
    },
    {
      "x": 0.07201,
      "y": 0.00794
    },
    {
      "x": 0.05778,
      "y": 0.01363
    },
    {
      "x": 0.05393,
      "y": 0.01545
    },
    {
      "x": 0.04354,
      "y": 0.02131
    },
    {
      "x": 0.03315,
      "y": 0.02865
    },
    {
      "x": 0.02889,
      "y": 0.03227
    },
    {
      "x": 0.02484,
      "y": 0.03615
    },
    {
      "x": 0.01964,
      "y": 0.04176
    },
    {
      "x": 0.01237,
      "y": 0.05186
    },
    {
      "x": 0.00935,
      "y": 0.0573
    },
    {
      "x": 0.00499,
      "y": 0.06748
    },
    {
      "x": 0.00322,
      "y": 0.07352
    },
    {
      "x": 0.00156,
      "y": 0.08103
    },
    {
      "x": 0.0001,
      "y": 0.0938
    },
    {
      "x": 0.0,
      "y": 0.10165
    },
    {
      "x": 0.00021,
      "y": 0.10829
    },
    {
      "x": 0.00145,
      "y": 0.1202
    },
    {
      "x": 0.00312,
      "y": 0.13012
    },
    {
      "x": 0.00572,
      "y": 0.14169
    },
    {
      "x": 0.00914,
      "y": 0.15411
    },
    {
      "x": 0.01133,
      "y": 0.16119
    },
    {
      "x": 0.01632,
      "y": 0.17465
    },
    {
      "x": 0.02193,
      "y": 0.18742
    },
    {
      "x": 0.02629,
      "y": 0.19605
    },
    {
      "x": 0.03336,
      "y": 0.20873
    },
    {
      "x": 0.04032,
      "y": 0.21978
    },
    {
      "x": 0.045,
      "y": 0.22685
    },
    {
      "x": 0.04656,
      "y": 0.22918
    },
    {
      "x": 0.05934,
      "y": 0.24739
    },
    {
      "x": 0.06568,
      "y": 0.25628
    },
    {
      "x": 0.0715,
      "y": 0.2643
    },
    {
      "x": 0.07565,
      "y": 0.27008
    },
    {
      "x": 0.08386,
      "y": 0.28165
    },
    {
      "x": 0.09353,
      "y": 0.29511
    },
    {
      "x": 0.10028,
      "y": 0.30451
    },
    {
      "x": 0.11535,
      "y": 0.32453
    },
    {
      "x": 0.12356,
      "y": 0.33489
    },
    {
      "x": 0.12865,
      "y": 0.34101
    },
    {
      "x": 0.13073,
      "y": 0.34352
    },
    {
      "x": 0.13717,
      "y": 0.35137
    },
    {
      "x": 0.14476,
      "y": 0.36034
    },
    {
      "x": 0.15058,
      "y": 0.3669
    },
    {
      "x": 0.15473,
      "y": 0.37121
    },
    {
      "x": 0.16419,
      "y": 0.37993
    },
    {
      "x": 0.1723,
      "y": 0.38597
    },
    {
      "x": 0.17863,
      "y": 0.38977
    },
    {
      "x": 0.18684,
      "y": 0.39348
    },
    {
      "x": 0.19287,
      "y": 0.39555
    },
    {
      "x": 0.20025,
      "y": 0.39719
    },
    {
      "x": 0.20545,
      "y": 0.39779
    },
    {
      "x": 0.21241,
      "y": 0.39805
    },
    {
      "x": 0.21802,
      "y": 0.3977
    },
    {
      "x": 0.22301,
      "y": 0.39701
    },
    {
      "x": 0.23153,
      "y": 0.39494
    },
    {
      "x": 0.23963,
      "y": 0.39192
    },
    {
      "x": 0.24535,
      "y": 0.38916
    },
    {
      "x": 0.24888,
      "y": 0.387
    },
    {
      "x": 0.2521,
      "y": 0.38468
    },
    {
      "x": 0.25616,
      "y": 0.38131
    },
    {
      "x": 0.26281,
      "y": 0.37467
    },
    {
      "x": 0.2678,
      "y": 0.36863
    },
    {
      "x": 0.2705,
      "y": 0.36474
    },
    {
      "x": 0.27268,
      "y": 0.36112
    },
    {
      "x": 0.27704,
      "y": 0.35189
    },
    {
      "x": 0.27902,
      "y": 0.34628
    },
    {
      "x": 0.28047,
      "y": 0.34041
    },
    {
      "x": 0.28131,
      "y": 0.33592
    },
    {
      "x": 0.28193,
      "y": 0.32729
    },
    {
      "x": 0.28182,
      "y": 0.32194
    },
    {
      "x": 0.28099,
      "y": 0.31478
    },
    {
      "x": 0.27808,
      "y": 0.30305
    },
    {
      "x": 0.27497,
      "y": 0.29502
    },
    {
      "x": 0.26987,
      "y": 0.2851
    },
    {
      "x": 0.26561,
      "y": 0.27845
    },
    {
      "x": 0.25616,
      "y": 0.26646
    },
    {
      "x": 0.24909,
      "y": 0.258
    },
    {
      "x": 0.24327,
      "y": 0.25127
    },
    {
      "x": 0.23776,
      "y": 0.24506
    },
    {
      "x": 0.22768,
      "y": 0.23358
    },
    {
      "x": 0.21667,
      "y": 0.22099
    },
    {
      "x": 0.20773,
      "y": 0.21089
    },
    {
      "x": 0.20243,
      "y": 0.20494
    },
    {
      "x": 0.19755,
      "y": 0.19924
    },
    {
      "x": 0.19131,
      "y": 0.19208
    },
    {
      "x": 0.18653,
      "y": 0.18647
    },
    {
      "x": 0.183,
      "y": 0.18224
    },
    {
      "x": 0.17697,
      "y": 0.17473
    },
    {
      "x": 0.1723,
      "y": 0.16844
    },
    {
      "x": 0.16793,
      "y": 0.16196
    },
    {
      "x": 0.16388,
      "y": 0.15489
    },
    {
      "x": 0.16003,
      "y": 0.146
    },
    {
      "x": 0.15889,
      "y": 0.14272
    },
    {
      "x": 0.15775,
      "y": 0.13677
    },
    {
      "x": 0.15744,
      "y": 0.13349
    },
    {
      "x": 0.15764,
      "y": 0.12952
    },
    {
      "x": 0.15899,
      "y": 0.12391
    },
    {
      "x": 0.16076,
      "y": 0.12003
    },
    {
      "x": 0.16325,
      "y": 0.11632
    },
    {
      "x": 0.16575,
      "y": 0.11356
    },
    {
      "x": 0.17178,
      "y": 0.10916
    },
    {
      "x": 0.17624,
      "y": 0.107
    },
    {
      "x": 0.17999,
      "y": 0.1057
    },
    {
      "x": 0.19017,
      "y": 0.10389
    },
    {
      "x": 0.19464,
      "y": 0.10372
    },
    {
      "x": 0.20378,
      "y": 0.10441
    },
    {
      "x": 0.21501,
      "y": 0.10665
    },
    {
      "x": 0.22259,
      "y": 0.10898
    },
    {
      "x": 0.22696,
      "y": 0.11054
    },
    {
      "x": 0.23361,
      "y": 0.11312
    },
    {
      "x": 0.24348,
      "y": 0.11735
    },
    {
      "x": 0.25075,
      "y": 0.12063
    },
    {
      "x": 0.2839,
      "y": 0.13521
    },
    {
      "x": 0.2944,
      "y": 0.13944
    },
    {
      "x": 0.30625,
      "y": 0.14376
    },
    {
      "x": 0.31768,
      "y": 0.14781
    },
    {
      "x": 0.32776,
      "y": 0.15126
    },
    {
      "x": 0.33472,
      "y": 0.15377
    },
    {
      "x": 0.34251,
      "y": 0.15661
    },
    {
      "x": 0.35124,
      "y": 0.16007
    },
    {
      "x": 0.3687,
      "y": 0.16818
    },
    {
      "x": 0.37992,
      "y": 0.17422
    },
    {
      "x": 0.39083,
      "y": 0.18095
    },
    {
      "x": 0.40289,
      "y": 0.18949
    },
    {
      "x": 0.42045,
      "y": 0.20442
    },
    {
      "x": 0.42689,
      "y": 0.2108
    },
    {
      "x": 0.43448,
      "y": 0.21883
    },
    {
      "x": 0.44882,
      "y": 0.23557
    },
    {
      "x": 0.45204,
      "y": 0.23936
    },
    {
      "x": 0.46119,
      "y": 0.25041
    },
    {
      "x": 0.46628,
      "y": 0.25662
    },
    {
      "x": 0.47615,
      "y": 0.26948
    },
    {
      "x": 0.47916,
      "y": 0.27431
    },
    {
      "x": 0.48311,
      "y": 0.28199
    },
    {
      "x": 0.48509,
      "y": 0.28777
    },
    {
      "x": 0.48592,
      "y": 0.29269
    },
    {
      "x": 0.48602,
      "y": 0.29614
    },
    {
      "x": 0.48519,
      "y": 0.30296
    },
    {
      "x": 0.48374,
      "y": 0.30779
    },
    {
      "x": 0.47948,
      "y": 0.31556
    },
    {
      "x": 0.47584,
      "y": 0.31987
    },
    {
      "x": 0.46846,
      "y": 0.326
    },
    {
      "x": 0.46378,
      "y": 0.32919
    },
    {
      "x": 0.45984,
      "y": 0.33161
    },
    {
      "x": 0.45329,
      "y": 0.3354
    },
    {
      "x": 0.45069,
      "y": 0.33687
    },
    {
      "x": 0.4404,
      "y": 0.34343
    },
    {
      "x": 0.43209,
      "y": 0.3499
    },
    {
      "x": 0.42544,
      "y": 0.35629
    },
    {
      "x": 0.41733,
      "y": 0.36604
    },
    {
      "x": 0.41359,
      "y": 0.37251
    },
    {
      "x": 0.41089,
      "y": 0.37812
    },
    {
      "x": 0.40372,
      "y": 0.39451
    },
    {
      "x": 0.39894,
      "y": 0.4053
    },
    {
      "x": 0.39613,
      "y": 0.41151
    },
    {
      "x": 0.39198,
      "y": 0.42057
    },
    {
      "x": 0.38876,
      "y": 0.42765
    },
    {
      "x": 0.38553,
      "y": 0.4342
    },
    {
      "x": 0.38044,
      "y": 0.4437
    },
    {
      "x": 0.37348,
      "y": 0.45517
    },
    {
      "x": 0.37254,
      "y": 0.45664
    },
    {
      "x": 0.36434,
      "y": 0.46993
    },
    {
      "x": 0.35956,
      "y": 0.47761
    },
    {
      "x": 0.35498,
      "y": 0.48503
    },
    {
      "x": 0.34989,
      "y": 0.49331
    },
    {
      "x": 0.34709,
      "y": 0.49797
    },
    {
      "x": 0.34158,
      "y": 0.50859
    },
    {
      "x": 0.33773,
      "y": 0.52015
    },
    {
      "x": 0.33742,
      "y": 0.52205
    },
    {
      "x": 0.33659,
      "y": 0.5305
    },
    {
      "x": 0.33659,
      "y": 0.53499
    },
    {
      "x": 0.33711,
      "y": 0.54215
    },
    {
      "x": 0.33846,
      "y": 0.55173
    },
    {
      "x": 0.33898,
      "y": 0.55423
    },
    {
      "x": 0.34106,
      "y": 0.56278
    },
    {
      "x": 0.34366,
      "y": 0.57045
    },
    {
      "x": 0.34553,
      "y": 0.57503
    },
    {
      "x": 0.34844,
      "y": 0.58124
    },
    {
      "x": 0.35322,
      "y": 0.58927
    },
    {
      "x": 0.35779,
      "y": 0.59556
    },
    {
      "x": 0.36631,
      "y": 0.60463
    },
    {
      "x": 0.37171,
      "y": 0.60903
    },
    {
      "x": 0.38023,
      "y": 0.61472
    },
    {
      "x": 0.39187,
      "y": 0.62059
    },
    {
      "x": 0.40289,
      "y": 0.62525
    },
    {
      "x": 0.41661,
      "y": 0.63051
    },
    {
      "x": 0.4244,
      "y": 0.63353
    },
    {
      "x": 0.44061,
      "y": 0.63974
    },
    {
      "x": 0.46254,
      "y": 0.64811
    },
    {
      "x": 0.4722,
      "y": 0.65183
    },
    {
      "x": 0.48821,
      "y": 0.65804
    },
    {
      "x": 0.50005,
      "y": 0.66261
    },
    {
      "x": 0.51128,
      "y": 0.66693
    },
    {
      "x": 0.51876,
      "y": 0.66977
    },
    {
      "x": 0.52728,
      "y": 0.67314
    },
    {
      "x": 0.54089,
      "y": 0.6784
    },
    {
      "x": 0.5517,
      "y": 0.68254
    },
    {
      "x": 0.56874,
      "y": 0.68919
    },
    {
      "x": 0.57986,
      "y": 0.69368
    },
    {
      "x": 0.58932,
      "y": 0.69764
    },
    {
      "x": 0.59742,
      "y": 0.70127
    },
    {
      "x": 0.61488,
      "y": 0.70921
    },
    {
      "x": 0.63047,
      "y": 0.71628
    },
    {
      "x": 0.64107,
      "y": 0.72103
    },
    {
      "x": 0.65073,
      "y": 0.72534
    },
    {
      "x": 0.67349,
      "y": 0.73553
    },
    {
      "x": 0.68565,
      "y": 0.74096
    },
    {
      "x": 0.69563,
      "y": 0.74545
    },
    {
      "x": 0.71215,
      "y": 0.75287
    },
    {
      "x": 0.72607,
      "y": 0.75908
    },
    {
      "x": 0.74124,
      "y": 0.76555
    },
    {
      "x": 0.75008,
      "y": 0.76909
    },
    {
      "x": 0.76265,
      "y": 0.77375
    },
    {
      "x": 0.77429,
      "y": 0.77781
    },
    {
      "x": 0.78167,
      "y": 0.78031
    },
    {
      "x": 0.78957,
      "y": 0.78298
    },
    {
      "x": 0.79923,
      "y": 0.78618
    },
    {
      "x": 0.80952,
      "y": 0.78971
    },
    {
      "x": 0.81471,
      "y": 0.79161
    },
    {
      "x": 0.82646,
      "y": 0.79644
    },
    {
      "x": 0.83228,
      "y": 0.79938
    },
    {
      "x": 0.84059,
      "y": 0.80481
    },
    {
      "x": 0.84464,
      "y": 0.80844
    },
    {
      "x": 0.8487,
      "y": 0.8137
    },
    {
      "x": 0.85129,
      "y": 0.81948
    },
    {
      "x": 0.85202,
      "y": 0.8225
    },
    {
      "x": 0.85223,
      "y": 0.82915
    },
    {
      "x": 0.85109,
      "y": 0.83527
    },
    {
      "x": 0.8489,
      "y": 0.84106
    },
    {
      "x": 0.84579,
      "y": 0.84658
    },
    {
      "x": 0.84288,
      "y": 0.85046
    },
    {
      "x": 0.84049,
      "y": 0.85322
    },
    {
      "x": 0.83778,
      "y": 0.8559
    },
    {
      "x": 0.833,
      "y": 0.85987
    },
    {
      "x": 0.82999,
      "y": 0.86194
    },
    {
      "x": 0.82718,
      "y": 0.86358
    },
    {
      "x": 0.81752,
      "y": 0.86781
    },
    {
      "x": 0.80588,
      "y": 0.87074
    },
    {
      "x": 0.80131,
      "y": 0.87143
    },
    {
      "x": 0.79372,
      "y": 0.87221
    },
    {
      "x": 0.78198,
      "y": 0.87247
    },
    {
      "x": 0.77117,
      "y": 0.87169
    },
    {
      "x": 0.76993,
      "y": 0.87152
    },
    {
      "x": 0.75891,
      "y": 0.86962
    },
    {
      "x": 0.75153,
      "y": 0.86781
    },
    {
      "x": 0.74623,
      "y": 0.86608
    },
    {
      "x": 0.73958,
      "y": 0.86366
    },
    {
      "x": 0.73231,
      "y": 0.86056
    },
    {
      "x": 0.72108,
      "y": 0.85486
    },
    {
      "x": 0.71038,
      "y": 0.84874
    },
    {
      "x": 0.70155,
      "y": 0.84356
    },
    {
      "x": 0.69459,
      "y": 0.83976
    },
    {
      "x": 0.6869,
      "y": 0.83622
    },
    {
      "x": 0.68035,
      "y": 0.83364
    },
    {
      "x": 0.67256,
      "y": 0.83105
    },
    {
      "x": 0.66227,
      "y": 0.82846
    },
    {
      "x": 0.65084,
      "y": 0.82673
    },
    {
      "x": 0.64491,
      "y": 0.82639
    },
    {
      "x": 0.63691,
      "y": 0.82639
    },
    {
      "x": 0.63109,
      "y": 0.8269
    },
    {
      "x": 0.62361,
      "y": 0.82829
    },
    {
      "x": 0.61322,
      "y": 0.83217
    },
    {
      "x": 0.60626,
      "y": 0.83674
    },
    {
      "x": 0.60158,
      "y": 0.84106
    },
    {
      "x": 0.59877,
      "y": 0.84451
    },
    {
      "x": 0.5969,
      "y": 0.84744
    },
    {
      "x": 0.59482,
      "y": 0.85132
    },
    {
      "x": 0.59327,
      "y": 0.85529
    },
    {
      "x": 0.59212,
      "y": 0.85995
    },
    {
      "x": 0.5914,
      "y": 0.86867
    },
    {
      "x": 0.59254,
      "y": 0.87807
    },
    {
      "x": 0.59514,
      "y": 0.88627
    },
    {
      "x": 0.59586,
      "y": 0.88808
    },
    {
      "x": 0.60044,
      "y": 0.89671
    },
    {
      "x": 0.6073,
      "y": 0.90595
    },
    {
      "x": 0.61997,
      "y": 0.91828
    },
    {
      "x": 0.6259,
      "y": 0.92286
    },
    {
      "x": 0.63275,
      "y": 0.92769
    },
    {
      "x": 0.6367,
      "y": 0.93037
    },
    {
      "x": 0.64419,
      "y": 0.93528
    },
    {
      "x": 0.64959,
      "y": 0.93874
    },
    {
      "x": 0.65957,
      "y": 0.94521
    },
    {
      "x": 0.67411,
      "y": 0.95539
    },
    {
      "x": 0.68658,
      "y": 0.96428
    },
    {
      "x": 0.69427,
      "y": 0.96963
    },
    {
      "x": 0.7003,
      "y": 0.97377
    },
    {
      "x": 0.70986,
      "y": 0.98007
    },
    {
      "x": 0.71745,
      "y": 0.98455
    },
    {
      "x": 0.72244,
      "y": 0.9874
    },
    {
      "x": 0.73033,
      "y": 0.9912
    },
    {
      "x": 0.73646,
      "y": 0.99361
    },
    {
      "x": 0.74644,
      "y": 0.99672
    },
    {
      "x": 0.75766,
      "y": 0.99905
    },
    {
      "x": 0.76619,
      "y": 0.99991
    },
    {
      "x": 0.76837,
      "y": 1.0
    },
    {
      "x": 0.77762,
      "y": 1.0
    },
    {
      "x": 0.78447,
      "y": 0.99957
    },
    {
      "x": 0.79892,
      "y": 0.99758
    },
    {
      "x": 0.80495,
      "y": 0.99638
    },
    {
      "x": 0.81087,
      "y": 0.99482
    },
    {
      "x": 0.82739,
      "y": 0.98947
    },
    {
      "x": 0.83799,
      "y": 0.98524
    },
    {
      "x": 0.84475,
      "y": 0.98222
    },
    {
      "x": 0.84786,
      "y": 0.98084
    },
    {
      "x": 0.85628,
      "y": 0.97679
    },
    {
      "x": 0.86636,
      "y": 0.9717
    },
    {
      "x": 0.8726,
      "y": 0.96842
    },
    {
      "x": 0.87966,
      "y": 0.96462
    },
    {
      "x": 0.88756,
      "y": 0.96039
    },
    {
      "x": 0.89982,
      "y": 0.95392
    },
    {
      "x": 0.90886,
      "y": 0.94918
    },
    {
      "x": 0.9178,
      "y": 0.94443
    },
    {
      "x": 0.9284,
      "y": 0.93874
    },
    {
      "x": 0.94097,
      "y": 0.93175
    },
    {
      "x": 0.94524,
      "y": 0.92916
    },
    {
      "x": 0.95854,
      "y": 0.92061
    },
    {
      "x": 0.96986,
      "y": 0.91173
    },
    {
      "x": 0.97412,
      "y": 0.90793
    },
    {
      "x": 0.98348,
      "y": 0.89818
    },
    {
      "x": 0.9867,
      "y": 0.89386
    },
    {
      "x": 0.99221,
      "y": 0.88437
    },
    {
      "x": 0.99553,
      "y": 0.87635
    },
    {
      "x": 0.99865,
      "y": 0.86453
    },
    {
      "x": 1.0,
      "y": 0.8546
    },
    {
      "x": 1.0,
      "y": 0.8477
    },
    {
      "x": 0.99865,
      "y": 0.83735
    },
    {
      "x": 0.99719,
      "y": 0.83087
    },
    {
      "x": 0.99512,
      "y": 0.8244
    },
    {
      "x": 0.9921,
      "y": 0.81733
    },
    {
      "x": 0.98784,
      "y": 0.80939
    },
    {
      "x": 0.98576,
      "y": 0.80585
    },
    {
      "x": 0.98171,
      "y": 0.79964
    },
    {
      "x": 0.97464,
      "y": 0.78954
    },
    {
      "x": 0.9709,
      "y": 0.78445
    },
    {
      "x": 0.9655,
      "y": 0.77746
    },
    {
      "x": 0.95885,
      "y": 0.76901
    },
    {
      "x": 0.95261,
      "y": 0.76107
    },
    {
      "x": 0.94731,
      "y": 0.75434
    },
    {
      "x": 0.93973,
      "y": 0.74467
    },
    {
      "x": 0.931,
      "y": 0.73345
    },
    {
      "x": 0.92986,
      "y": 0.73207
    },
    {
      "x": 0.91687,
      "y": 0.71542
    },
    {
      "x": 0.90938,
      "y": 0.70584
    },
    {
      "x": 0.90408,
      "y": 0.69911
    },
    {
      "x": 0.89691,
      "y": 0.68996
    },
    {
      "x": 0.88777,
      "y": 0.67832
    },
    {
      "x": 0.88091,
      "y": 0.66969
    },
    {
      "x": 0.86886,
      "y": 0.65415
    },
    {
      "x": 0.85659,
      "y": 0.63836
    },
    {
      "x": 0.85088,
      "y": 0.63094
    }
  ],
  "sectors": [
    {
      "sector": 1,
      "start_index": 0,
      "end_index": 128,
      "start_dist": 0.0,
      "end_dist": 0.33333
    },
    {
      "sector": 2,
      "start_index": 129,
      "end_index": 287,
      "start_dist": 0.33333,
      "end_dist": 0.66667
    },
    {
      "sector": 3,
      "start_index": 288,
      "end_index": 441,
      "start_dist": 0.66667,
      "end_dist": 1.0
    }
  ]
}